[
    {
        "Title": "Associate Programmer",
        "Company": "Sheetz",
        "Description": "None",
        "Salary": "None"
    },
    {
        "Title": "Junior Software Engineer - Back End",
        "Company": "OneMain Financial",
        "Description": "None",
        "Salary": "None"
    },
    {
        "Title": "Architect, IT Remote",
        "Company": "Centene Corporation",
        "Description": "None",
        "Salary": "None"
    },
    {
        "Title": "Junior Software Engineer - Front End",
        "Company": "OneMain Financial",
        "Description": "None",
        "Salary": "None"
    },
    {
        "Title": "Data Engineering Manager",
        "Company": "Vanguard",
        "Description": "None",
        "Salary": "None"
    },
    {
        "Title": "Information Security Normalization Analyst",
        "Company": "Vanguard",
        "Description": "None",
        "Salary": "None"
    },
    {
        "Title": "Jr. Software Developer",
        "Company": "CORVID Technologies",
        "Description": "None",
        "Salary": "None"
    },
    {
        "Title": "Computer Technician",
        "Company": "McDonald's",
        "Description": "None",
        "Salary": "From $40,000 a year"
    },
    {
        "Title": "Technology Support Specialist",
        "Company": "ACL Digital",
        "Description": "None",
        "Salary": "$25 - $32 an hour"
    },
    {
        "Title": "IT Application Associate Programmer - Pittsburgh, PA",
        "Company": "Sheetz",
        "Description": "None",
        "Salary": "None"
    },
    {
        "Title": "Audit Associate | Charlotte Summer/Fall 2022",
        "Company": "KPMG",
        "Description": "None",
        "Salary": "None"
    },
    {
        "Title": "Software Engineer",
        "Company": "Ally Financial",
        "Description": "None",
        "Salary": "None"
    },
    {
        "Title": "Apple Support College Program -University of North Carolina,...",
        "Company": "Apple",
        "Description": "None",
        "Salary": "None"
    },
    {
        "Title": "Prospect Researcher",
        "Company": "UNC Charlotte",
        "Description": "None",
        "Salary": "None"
    },
    {
        "Title": "Systems Software Engineer",
        "Company": "Actalent",
        "Description": "None",
        "Salary": "$40 - $60 an hour"
    }
]